Metadata-Version: 2.1
Name: hackfunc
Version: 1.0.0
Summary: A toolkit for basic security checks and scans
Home-page: https://github.com/Zierax/HackFunction
Author: Zierax
Author-email: zs.01117875692@gmail.com
License: MIT
Project-URL: Documentation, https://github.com/Zierax/HackFunction/docs
Project-URL: Source, https://github.com/Zierax/HackFunction
Project-URL: Tracker, https://github.com/Zierax/HackFunction/issues
Classifier: Programming Language :: Python :: 3
Classifier: License :: OSI Approved :: MIT License
Classifier: Operating System :: OS Independent
Requires-Python: >=3.6
Provides-Extra: testing
